heap_class/__init__.py
heap_class-0.9.1b2.dist-info/METADATA
heap_class-0.9.1b2.dist-info/WHEEL
heap_class-0.9.1b2.dist-info/licenses/LICENSE
heap_class-0.9.1b2.dist-info/RECORD
