Metadata-Version: 2.4
Name: heap-class
Version: 0.9.1b2
Summary: A list-like implementation of heap/PriorityQueue
Project-URL: Homepage, https://github.com/mscuthbert/heap_class
Project-URL: Documentation, https://github.com/mscuthbert/heap_class#readme
Project-URL: Issues, https://github.com/mscuthbert/heap_class/issues
Project-URL: Source, https://github.com/mscuthbert/heap_class
Author-email: Michael Scott Asato Cuthbert <michael.asato.cuthbert@gmail.com>
License-Expression: MIT
License-File: LICENSE
Keywords: PriorityQueue,heap,sorting
Classifier: Development Status :: 4 - Beta
Classifier: License :: OSI Approved :: MIT License
Classifier: Programming Language :: Python
Classifier: Programming Language :: Python :: 3.9
Classifier: Programming Language :: Python :: 3.10
Classifier: Programming Language :: Python :: 3.11
Classifier: Programming Language :: Python :: 3.12
Classifier: Programming Language :: Python :: 3.13
Classifier: Programming Language :: Python :: Implementation :: CPython
Classifier: Programming Language :: Python :: Implementation :: PyPy
Requires-Python: >=3.9
